elphmod/MPI.py
elphmod/__init__.py
elphmod/bravais.py
elphmod/diagrams.py
elphmod/dispersion.py
elphmod/dos.py
elphmod/el.py
elphmod/elel.py
elphmod/eliashberg.py
elphmod/elph.py
elphmod/md.py
elphmod/misc.py
elphmod/occupations.py
elphmod/ph.py
elphmod/plot.py
elphmod/models/__init__.py
elphmod/models/chain.py
elphmod/models/graphene.py
elphmod/models/tas2.py
elphmod-0.31.dist-info/entry_points.txt
elphmod-0.31.dist-info/licenses/LICENSE
elphmod-0.31.dist-info/WHEEL
elphmod-0.31.dist-info/METADATA
elphmod-0.31.dist-info/RECORD
