Metadata-Version: 2.4
Name: elphmod
Version: 0.31
Summary: Python modules for electron-phonon models
Author: elphmod Developers
Requires-Python: >=3.5
Classifier: License :: OSI Approved :: GNU General Public License v3 or later (GPLv3+)
Classifier: Programming Language :: Python :: 3
License-File: LICENSE
Requires-Dist: numpy
Requires-Dist: scipy
Project-URL: Homepage, https://github.com/janberges/elphmod
